{
    "productos": [
        {
            "productId": 1,
            "articulo": "zapatilla nike",
            "description": "zapatillas de alta calidad",
            "imgUrl": "https://static.nike.com/a/images/c_limit,w_592,f_auto/t_product_v1/d0b94722-d603-4e66-829c-51f1801ec3fa/air-max-pulse-zapatillas-DtVTbL.png",
            "price": 1500,
            "category": "zapatillas",
            "categoryId":1
        },
        {
            "productId": 2,
            "articulo": "zapatilla nike",
            "description": "zapatillas de alta calidad",
            "imgUrl": "https://static.nike.com/a/images/c_limit,w_592,f_auto/t_product_v1/89ff81a5-c881-4aa8-a4c0-8880583636ca/air-max-90-se-zapatillas-2Dd8X5.png",
            "price": 1600,
            "category": "zapatillas",
            "categoryId":1
        },
        {
            "productId": 3,
            "articulo": "zapatilla nike",
            "description": "zapatillas de alta calidad",
            "imgUrl": "https://static.nike.com/a/images/c_limit,w_592,f_auto/t_product_v1/90af2c02-5d95-464a-92c7-4454350960d5/air-max-97-se-zapatillas-Cd8fsS.png",
            "price": 1700,
            "category": "zapatillas",
            "categoryId":1
        },
        {
            "productId": 4,
            "articulo": "zapatilla nike",
            "description": "zapatillas de alta calidad",
            "imgUrl": "https://static.nike.com/a/images/c_limit,w_592,f_auto/t_product_v1/2b292473-22d9-44ba-a567-5158185bdb18/air-max-90-zapatillas-kw0HCK.png",
            "price": 1800,
            "category": "zapatillas",
            "categoryId":1
        },
        {
            "productId": 5,
            "articulo": "remera nike",
            "description": "remera nike",
            "imgUrl": "https://static.nike.com/a/images/c_limit,w_592,f_auto/t_product_v1/77b79747-b5bd-4de4-8212-1630b09fdfdd/air-jordan-wordmark-camiseta-6x6JTt.png",
            "price": 2000,
            "category": "remera",
            "categoryId":2
        },
        {
            "productId": 6,
            "articulo": "remera nike",
            "description": "remera nike",
            "imgUrl": "https://static.nike.com/a/images/c_limit,w_592,f_auto/t_product_v1/21e25478-cba0-47bb-aad6-bb6cc7287bf1/los-angeles-lakers-camiseta-de-la-nba-9pDfDt.png",
            "price": 2100,
            "category": "remera",
            "categoryId":2
        },
        {
            "productId": 7,
            "articulo": "remera nike",
            "description": "remera nike",
            "imgUrl": "https://static.nike.com/a/images/c_limit,w_592,f_auto/t_product_v1/024c4d57-e7da-4c08-8da6-a3112d2b7575/jordan-essentials-camiseta-oversize-con-estampado-21kKp5.png",
            "price": 2200,
            "category": "remera",
            "categoryId":2
        }, 
        {
            "productId": 8,
            "articulo": "pantalon nike",
            "description": "pantalon nike",
            "imgUrl": "https://static.nike.com/a/images/c_limit,w_592,f_auto/t_product_v1/2fc731a1-c21f-46e0-bd67-d215d574774d/jordan-dri-fit-sport-diamond-pantalon-corto-qFZNR9.png",
            "price": 2300,
            "category": "pantalon",
            "categoryId":3
        }, 
        {
            "productId": 9,
            "articulo": "pantalon nike",
            "description": "pantalon nike",
            "imgUrl": "https://static.nike.com/a/images/c_limit,w_592,f_auto/t_product_v1/b7eabed4-5de6-4e43-98b2-4d9f5c4a536e/sportswear-club-pantalon-corto-de-sarga-CgDmmM.png",
            "price": 2400,
            "category": "pantalon",
            "categoryId":3
        },
        {
            "productId": 10,
            "articulo": "pantalon nike",
            "description": "pantalon nike",
            "imgUrl": "https://static.nike.com/a/images/c_limit,w_592,f_auto/t_product_v1/5fedff01-053a-4cbd-8d17-d4dd62a0c360/sportswear-tech-fleece-pantalon-corto-zlzz3G.png",
            "price": 2500,
            "category": "pantalon",
            "categoryId":3
        }
    ]
}